chronai/__init__.py
chronai/common/__init__.py
chronai/core/__init__.py
chronai/core/constants.py
chronai/core/types.py
chronai/core/validators.py
chronai/heirarchy_tree/README.md
chronai/heirarchy_tree/__init__.py
chronai/sessionization/README.md
chronai/sessionization/__init__.py
chronai/sessionization/_core.py
chronai/sessionization/semantic.py
chronai/sessionization/windowed.py
chronai/topic_trends/README.md
chronai/topic_trends/__init__.py
chronai-0.0.4.dist-info/METADATA
chronai-0.0.4.dist-info/WHEEL
chronai-0.0.4.dist-info/licenses/LICENSE
chronai-0.0.4.dist-info/RECORD
